multimapwithttl/__init__.py
multimapwithttl/multimapwithttl.py
python_multimapwithttl-0.1.0.dist-info/LICENSE
python_multimapwithttl-0.1.0.dist-info/WHEEL
python_multimapwithttl-0.1.0.dist-info/METADATA
python_multimapwithttl-0.1.0.dist-info/RECORD
